tornado_instant_webapi/__init__.py
tornado_instant_webapi/api_handler.py
tornado_instant_webapi/change_case.py
tornado_instant_webapi/converter.py
tornado_instant_webapi/make_application.py
tornado_instant_webapi/make_handlers.py
tornado_instant_webapi-1.0.0.dist-info/DESCRIPTION.rst
tornado_instant_webapi-1.0.0.dist-info/METADATA
tornado_instant_webapi-1.0.0.dist-info/RECORD
tornado_instant_webapi-1.0.0.dist-info/WHEEL
tornado_instant_webapi-1.0.0.dist-info/metadata.json
tornado_instant_webapi-1.0.0.dist-info/top_level.txt
