Metadata-Version: 2.0
Name: tornado-instant-webapi
Version: 1.0.0
Summary: The library for automatically generating web API from Python object based on Tornado.
Home-page: https://github.com/Hiroshiba/tornado_instant_webapi
Author: Kazuyuki Hiroshiba
Author-email: hihokaruta@gmail.com
License: MIT License
Platform: UNKNOWN
Classifier: Programming Language :: Python :: 3.5
Classifier: Programming Language :: Python :: 3.6
Classifier: License :: OSI Approved :: MIT License
Requires-Dist: tornado
